morgan_course_data/__init__.py
morgan_course_data/api.py
morgan_course_data/db.py
morgan_course_data/types.py
morgan_course_data/utils.py
morgan_course_data-0.1.2.dist-info/METADATA
morgan_course_data-0.1.2.dist-info/WHEEL
morgan_course_data-0.1.2.dist-info/top_level.txt
morgan_course_data-0.1.2.dist-info/RECORD
