Metadata-Version: 2.1
Name: morgan_course_data
Version: 0.1.2
Summary: Python package for querying Morgan State University course data.
Home-page: https://github.com/clydewtt/morgan-course-api
Author: Clyde Tandjong
Author-email: cltandjong@gmail.com
Classifier: Programming Language :: Python :: 3
Classifier: License :: OSI Approved :: MIT License
Requires-Dist: pymongo
Requires-Dist: bson
Provides-Extra: dev
Requires-Dist: pytest>=6.0.0; extra == "dev"
